tplink_omada_client/__init__.py
tplink_omada_client/clients.py
tplink_omada_client/definitions.py
tplink_omada_client/devices.py
tplink_omada_client/exceptions.py
tplink_omada_client/omadaapiconnection.py
tplink_omada_client/omadaclient.py
tplink_omada_client/omadasiteclient.py
tplink_omada_client/py.typed
tplink_omada_client/cli/__init__.py
tplink_omada_client/cli/__main__.py
tplink_omada_client/cli/command_access_point.py
tplink_omada_client/cli/command_access_points.py
tplink_omada_client/cli/command_block_client.py
tplink_omada_client/cli/command_certificate.py
tplink_omada_client/cli/command_client.py
tplink_omada_client/cli/command_clients.py
tplink_omada_client/cli/command_controller_info.py
tplink_omada_client/cli/command_default.py
tplink_omada_client/cli/command_devices.py
tplink_omada_client/cli/command_gateway.py
tplink_omada_client/cli/command_known_clients.py
tplink_omada_client/cli/command_poe.py
tplink_omada_client/cli/command_reboot.py
tplink_omada_client/cli/command_reconnect_client.py
tplink_omada_client/cli/command_set_client_name.py
tplink_omada_client/cli/command_set_device_led.py
tplink_omada_client/cli/command_switch.py
tplink_omada_client/cli/command_switch_ports.py
tplink_omada_client/cli/command_switches.py
tplink_omada_client/cli/command_target.py
tplink_omada_client/cli/command_targets.py
tplink_omada_client/cli/command_unblock_client.py
tplink_omada_client/cli/command_wan.py
tplink_omada_client/cli/config.py
tplink_omada_client/cli/util.py
tplink_omada_client-1.5.3.dist-info/METADATA
tplink_omada_client-1.5.3.dist-info/WHEEL
tplink_omada_client-1.5.3.dist-info/entry_points.txt
tplink_omada_client-1.5.3.dist-info/licenses/LICENSE
tplink_omada_client-1.5.3.dist-info/RECORD
