Metadata-Version: 2.4
Name: tplink_omada_client
Version: 1.5.3
Summary: Python wrapper for TP-Link Omada SDN Controller API (OC200/OC300/Software Controller)
Project-URL: Homepage, https://github.com/MarkGodwin/tplink-omada-api
Project-URL: Bug Tracker, https://github.com/MarkGodwin/tplink-omada-api/issues
Author-email: Mark Godwin <10632972+MarkGodwin@users.noreply.github.com>
License-File: LICENSE
Classifier: License :: OSI Approved :: MIT License
Classifier: Operating System :: OS Independent
Classifier: Programming Language :: Python :: 3.13
Requires-Python: >=3.13
Requires-Dist: aiohttp<4,>=3.12.2
Requires-Dist: awesomeversion>=25.8.0
